orchestrator_service/__init__.py
orchestrator_service/exc.py
orchestrator_service/message/__init__.py
orchestrator_service/message/custom.py
orchestrator_service/message/exc.py
orchestrator_service/message/message.py
orchestrator_service/orchestrator/__init__.py
orchestrator_service/orchestrator/exc.py
orchestrator_service/orchestrator/orchestrator.py
orchestrator_service/orchestrator/block/__init__.py
orchestrator_service/orchestrator/block/block.py
orchestrator_service/orchestrator/block/exc.py
orchestrator_service/orchestrator/flow/__init__.py
orchestrator_service/orchestrator/flow/exc.py
orchestrator_service/orchestrator/flow/flow.py
orchestrator_service/orchestrator/utils/__init__.py
orchestrator_service/orchestrator/utils/incorrect.py
orchestrator_service/service/__init__.py
orchestrator_service/service/default.py
orchestrator_service/service/exc.py
orchestrator_service/service/service.py
orchestrator_service/service/to_extends.py
orchestrator_service/utils/__init__.py
orchestrator_service-0.0.15.dist-info/LICENSE
orchestrator_service-0.0.15.dist-info/METADATA
orchestrator_service-0.0.15.dist-info/WHEEL
orchestrator_service-0.0.15.dist-info/top_level.txt
orchestrator_service-0.0.15.dist-info/RECORD
