Metadata-Version: 2.1
Name: orchestrator-service
Version: 0.0.15
Summary: orchestrator_service for microservices architecture
Home-page: https://github.com/Shchusia/orchestrator
Author: Denis Shchutkiy
Author-email: denisshchutskyi@gmail.com
License: UNKNOWN
Keywords: pip,orchestrator_service
Platform: UNKNOWN
License-File: LICENSE
